claude_team/__init__.py
claude_team/events.py
claude_team/idle_detection.py
claude_team/poller.py
claude_team_mcp/__init__.py
claude_team_mcp/__main__.py
claude_team_mcp/colors.py
claude_team_mcp/config.py
claude_team_mcp/config_cli.py
claude_team_mcp/formatting.py
claude_team_mcp/idle_detection.py
claude_team_mcp/iterm_utils.py
claude_team_mcp/names.py
claude_team_mcp/profile.py
claude_team_mcp/registry.py
claude_team_mcp/server.py
claude_team_mcp/session_state.py
claude_team_mcp/subprocess_cache.py
claude_team_mcp/worker_prompt.py
claude_team_mcp/worktree.py
claude_team_mcp/cli_backends/__init__.py
claude_team_mcp/cli_backends/base.py
claude_team_mcp/cli_backends/claude.py
claude_team_mcp/cli_backends/codex.py
claude_team_mcp/issue_tracker/__init__.py
claude_team_mcp/schemas/__init__.py
claude_team_mcp/schemas/codex.py
claude_team_mcp/terminal_backends/__init__.py
claude_team_mcp/terminal_backends/base.py
claude_team_mcp/terminal_backends/iterm.py
claude_team_mcp/terminal_backends/tmux.py
claude_team_mcp/tools/__init__.py
claude_team_mcp/tools/adopt_worker.py
claude_team_mcp/tools/annotate_worker.py
claude_team_mcp/tools/check_idle_workers.py
claude_team_mcp/tools/close_workers.py
claude_team_mcp/tools/discover_workers.py
claude_team_mcp/tools/examine_worker.py
claude_team_mcp/tools/issue_tracker_help.py
claude_team_mcp/tools/list_workers.py
claude_team_mcp/tools/list_worktrees.py
claude_team_mcp/tools/message_workers.py
claude_team_mcp/tools/poll_worker_changes.py
claude_team_mcp/tools/read_worker_logs.py
claude_team_mcp/tools/spawn_workers.py
claude_team_mcp/tools/wait_idle_workers.py
claude_team_mcp/utils/__init__.py
claude_team_mcp/utils/constants.py
claude_team_mcp/utils/errors.py
claude_team_mcp/utils/worktree_detection.py
claude_team_mcp-0.8.0.dist-info/METADATA
claude_team_mcp-0.8.0.dist-info/WHEEL
claude_team_mcp-0.8.0.dist-info/entry_points.txt
claude_team_mcp-0.8.0.dist-info/RECORD
