Metadata-Version: 2.4
Name: claude-team-mcp
Version: 0.8.0
Summary: MCP server for managing multiple Claude Code sessions via iTerm2
Project-URL: Homepage, https://github.com/Martian-Engineering/claude-team
Project-URL: Repository, https://github.com/Martian-Engineering/claude-team
Project-URL: Documentation, https://github.com/Martian-Engineering/claude-team#readme
Project-URL: Issues, https://github.com/Martian-Engineering/claude-team/issues
Project-URL: Changelog, https://github.com/Martian-Engineering/claude-team/releases
Author-email: Josh Lehman <josh@martianengineering.com>
Maintainer-email: Josh Lehman <josh@martianengineering.com>
License: MIT
Keywords: ai,anthropic,automation,claude,claude-code,iterm2,mcp,multi-agent,orchestration
Classifier: Development Status :: 3 - Alpha
Classifier: Environment :: MacOS X
Classifier: Intended Audience :: Developers
Classifier: License :: OSI Approved :: MIT License
Classifier: Operating System :: MacOS
Classifier: Programming Language :: Python :: 3
Classifier: Programming Language :: Python :: 3.11
Classifier: Programming Language :: Python :: 3.12
Classifier: Programming Language :: Python :: 3.13
Classifier: Topic :: Software Development :: Libraries :: Python Modules
Classifier: Topic :: System :: Distributed Computing
Classifier: Typing :: Typed
Requires-Python: >=3.11
Requires-Dist: iterm2>=2.7
Requires-Dist: mcp>=1.0.0
Requires-Dist: msgspec>=0.19.0
